sum_pkg/__init__.py
sum_pkg/sum.py
sum_pkg-0.1.0.dist-info/METADATA
sum_pkg-0.1.0.dist-info/WHEEL
sum_pkg-0.1.0.dist-info/top_level.txt
sum_pkg-0.1.0.dist-info/RECORD
