Metadata-Version: 2.1
Name: sum-pkg
Version: 0.1.0
Summary: My Python Library for summation
Home-page: UNKNOWN
Author: Pratyusha
Author-email: UNKNOWN
License: UNKNOWN
Platform: UNKNOWN
